CHANGES.txt
LICENSE.txt
MANIFEST.in
README.rst
contributors.txt
setup.py
tinfiltering/__init__.py
tinfiltering/command_line.py
tinfiltering/criterion.py
tinfiltering/filter.py
tinfiltering.egg-info/PKG-INFO
tinfiltering.egg-info/SOURCES.txt
tinfiltering.egg-info/dependency_links.txt
tinfiltering.egg-info/entry_points.txt
tinfiltering.egg-info/not-zip-safe
tinfiltering.egg-info/requires.txt
tinfiltering.egg-info/top_level.txt
tinfiltering/test/__init__.py
tinfiltering/test/test.py
tinfiltering/test/test_data.npy
tinfiltering/test/test_data2.npy
tinfiltering/tin/__init__.py
tinfiltering/tin/basic_info.py
tinfiltering/tin/create.py
tinfiltering/tin/params.py
tinfiltering/tin/unpack.py