Metadata-Version: 1.1
Name: tinfiltering
Version: 0.1.4
Summary: Filters a set of points in a 2D space.
Home-page: https://bitbucket.org/matt_bv/tinfiltering
Author: Matheus Boni Vicari
Author-email: matheus.boni.vicari@gmail.com
License: LICENSE.txt
Keywords: data filtering TIN delaunay triangulation noise removal
Platform: UNKNOWN
Classifier: Programming Language :: Python
Classifier: Topic :: Scientific/Engineering
